talisman/__init__.py
talisman/talisman.py
talisman/talisman_test.py
talisman-0.1.0.dist-info/DESCRIPTION.rst
talisman-0.1.0.dist-info/METADATA
talisman-0.1.0.dist-info/metadata.json
talisman-0.1.0.dist-info/RECORD
talisman-0.1.0.dist-info/top_level.txt
talisman-0.1.0.dist-info/WHEEL
