Metadata-Version: 1.0
Name: talisman
Version: 0.1.0
Summary: HTTP security headers for Flask.
Home-page: https://github.com/GoogleCloudPlatform/flask-talisman
Author: Jon Wayne Parrott
Author-email: jonwayne@google.com
License: Apache Software License
Keywords: flask security https xss
Platform: UNKNOWN
Classifier: Development Status :: 3 - Alpha
Classifier: Intended Audience :: Developers
Classifier: Topic :: Software Development :: Libraries :: Python Modules
Classifier: License :: OSI Approved :: Apache Software License
Classifier: Programming Language :: Python
Classifier: Programming Language :: Python :: 2
Classifier: Programming Language :: Python :: 3
Classifier: Programming Language :: Python :: 2.7
Classifier: Programming Language :: Python :: 3.4
Classifier: Programming Language :: Python :: 3.5
Classifier: Operating System :: POSIX
Classifier: Operating System :: MacOS
Classifier: Operating System :: Unix
